icdar21_mapseg_eval/__init__.py
icdar21_mapseg_eval/__main__.py
icdar21_mapseg_eval/cli.py
icdar21_mapseg_eval/coco.py
icdar21_mapseg_eval/haussdorff.py
icdar21_mapseg_eval/iou.py
icdar21_mapseg_eval/point_detection.py
icdar21_mapseg_eval-1.0.4.dist-info/entry_points.txt
icdar21_mapseg_eval-1.0.4.dist-info/LICENSE
icdar21_mapseg_eval-1.0.4.dist-info/WHEEL
icdar21_mapseg_eval-1.0.4.dist-info/METADATA
icdar21_mapseg_eval-1.0.4.dist-info/RECORD
